dagster_datacontract/__init__.py
dagster_datacontract/description/__init__.py
dagster_datacontract/description/description.py
dagster_datacontract/metadata/__init__.py
dagster_datacontract/metadata/links.py
dagster_datacontract/metadata/server_information.py
dagster_datacontract/metadata/table_colums.py
dagster_datacontract/owners/__init__.py
dagster_datacontract/tags/__init__.py
dagster_datacontract/tags/tags.py
dagster_datacontract/utils/__init__.py
dagster_datacontract/utils/combine_strings.py
dagster_datacontract/utils/paths.py
dagster_datacontract-0.5.0.dist-info/licenses/LICENSE
dagster_datacontract-0.5.0.dist-info/METADATA
dagster_datacontract-0.5.0.dist-info/WHEEL
dagster_datacontract-0.5.0.dist-info/top_level.txt
dagster_datacontract-0.5.0.dist-info/RECORD
