Metadata-Version: 2.4
Name: dagster-datacontract
Version: 0.5.0
Summary: Load metadata and asset check spesifications from data contracts.
Author-email: Fredrik Bakken <fredrik@dataheim.io>
Requires-Python: >=3.10
License-File: LICENSE
Requires-Dist: dagster>=1.10.10
Requires-Dist: datacontract-cli>=0.10.24
Requires-Dist: loguru>=0.7.3
Dynamic: license-file
